{
   "files" : {
      "file:id:017cb5c9-2a7a-4987-aaf5-1aff79a8298d" : {
         "desc" : "",
         "file_name" : "ba-o1-302031_g2-000006.xml",
         "length" : 3507,
         "mime" : "application/rdf\u002Bxml",
         "sha256" : "92077d9e5a4bdad922dfa656870802ea5c3bc44e5e584f08037ec4aa38405147",
         "time" : 1735219934,
         "title" : "メタデータ（詳細）",
         "type" : "file",
         "url" : "https://catalog.registries.digital.go.jp/rc/dataset/ba-o1-302031_g2-000006.xml"
      },
      "file:id:98c51ea5-669b-4708-ab4b-d49ad69d2d1a" : {
         "desc" : "",
         "file_name" : "base_registry_address",
         "length" : 58025,
         "mime" : "text/html; charset=utf-8",
         "sha256" : "30c7d445fb2b802913ee6883807aaa76a0a94285ea002f92468351d812828046",
         "time" : 1735219785,
         "title" : "リソース定義",
         "type" : "file",
         "url" : "https://www.digital.go.jp/policies/base_registry_address"
      },
      "file:id:b1156741-6247-49d8-8b94-ed354a242e20" : {
         "desc" : "",
         "file_name" : "mt_town_pos_city302031.csv.zip",
         "length" : 1955,
         "mime" : "application/zip",
         "sha256" : "0bb33a8e275e09e078062cfe55549478ae11cba2518f1b57de2e11c4960dbcb8",
         "time" : 1735219933,
         "title" : "和歌山県 橋本市 町字マスター位置参照拡張 データセット",
         "type" : "file",
         "url" : "https://catalog.registries.digital.go.jp/rsc/address/mt_town_pos_city302031.csv.zip"
      },
      "meta:activity.html" : {
         "desc" : "",
         "length" : 11303,
         "mime" : "text/html; charset=utf-8",
         "sha256" : "7678c59c7bd19c9e0c29e2b8a0e112e91218e39aac0b1ff637f3e62365d78ea8",
         "time" : 1735219931,
         "title" : "",
         "type" : "meta",
         "url" : "https://catalog.registries.digital.go.jp/rc/dataset/activity/ba-o1-302031_g2-000006"
      },
      "meta:ckan.json" : {
         "desc" : "",
         "length" : 5643,
         "mime" : "application/json;charset=utf-8",
         "sha256" : "33c1dce22c5fbaf40475ed2423fc18b88a79899786a2b47e882cc077282ddbe5",
         "time" : 1710301285.68501,
         "title" : "和歌山県 橋本市 町字マスター位置参照拡張 データセット",
         "type" : "meta",
         "url" : "https://catalog.registries.digital.go.jp/rc/api/action/package_show?id=ba-o1-302031_g2-000006"
      }
   },
   "legal" : {
      "is_free" : "unknown",
      "legal" : [
         {
            "dir" : "ltr",
            "full_url" : "https://creativecommons.org/licenses/by/4.0/",
            "is_free" : "free",
            "key" : "CC-BY-4.0",
            "label" : "Creative Commons Attribution 4.0 International",
            "lang" : "en",
            "notice" : {
               "holder" : {
                  "dir" : "auto",
                  "lang" : "ja",
                  "value" : "和歌山県",
                  "writing_mode" : "horizontal-tb"
               },
               "need_modified_flag" : 1,
               "title" : {
                  "dir" : "auto",
                  "lang" : "ja",
                  "value" : "和歌山県 橋本市 町字マスター位置参照拡張 データセット",
                  "writing_mode" : "horizontal-tb"
               },
               "url" : "https://catalog.registries.digital.go.jp/rc/dataset/ba-o1-302031_g2-000006"
            },
            "source_type" : "package",
            "source_url" : "https://catalog.registries.digital.go.jp/rc/api/action/package_show?id=ba-o1-302031_g2-000006",
            "type" : "license",
            "writing_mode" : "horizontal-tb"
         },
         {
            "dir" : "auto",
            "is_free" : "unknown",
            "key" : "-ddsd-unknown",
            "lang" : "ja",
            "source_type" : "site",
            "source_url" : "https://catalog.registries.digital.go.jp/rc/terms",
            "type" : "site_terms",
            "writing_mode" : "horizontal-tb"
         },
         {
            "dir" : "ltr",
            "is_free" : "neutral",
            "key" : "-ddsd-disclaimer",
            "lang" : "ja",
            "notice" : {
               "template" : {
                  "dir" : "ltr",
                  "lang" : "ja",
                  "value" : "これらの法的な表示はソフトウェアにより機械的に抽出・生成したものです。ソフトウェアの制作者はその正確性、完全性、その他を一切保証しません。",
                  "writing_mode" : "horizontal-tb"
               }
            },
            "source_type" : "sniffer",
            "type" : "disclaimer",
            "writing_mode" : "horizontal-tb"
         }
      ]
   },
   "length" : 80433,
   "mirrorzip" : {
      "length" : 30928,
      "set" : "nonfree-1",
      "sha256" : "bc5f4fa52a307ae8fd9a39e4ee95a2560c4533a02b7bc5e98f9375f7759c330f"
   },
   "package" : {
      "author" : "",
      "ckan_api_url" : "https://catalog.registries.digital.go.jp/rc/api/action/package_show?id=ba-o1-302031_g2-000006",
      "desc" : "",
      "org" : "和歌山県",
      "page_url" : "https://catalog.registries.digital.go.jp/rc/dataset/ba-o1-302031_g2-000006",
      "tags" : [
         "和歌山県",
         "土地・地図",
         "住所情報",
         "市区町村",
         "都道府県"
      ],
      "time" : 1710301285.68501,
      "title" : "和歌山県 橋本市 町字マスター位置参照拡張 データセット"
   },
   "ref_key_text" : "6\u001C2ed77531006a8b6b1e8748ec8d7e86762da1060548a6af2414d203652f70bc3f\u001Cunknown\u001C0\u001C0"
}
