{
   "files" : {
      "file:id:1ff871d4-9be0-4380-a4f0-fea188b39db6" : {
         "desc" : "ベース・レジストリ（アドレス）のリソース定義です。（外部サイトが開きます）",
         "file_name" : "base_registry_address",
         "length" : 46393,
         "mime" : "text/html; charset=utf-8",
         "sha256" : "04eaa48795c92a024dd9de62c9599d5f7215ebbf3bc99cb88dc06dff450191ca",
         "time" : 1733952332,
         "title" : "リソース定義",
         "type" : "file",
         "url" : "https://www.digital.go.jp/policies/base_registry_address"
      },
      "file:id:4231f4d3-09d9-457e-81dd-69837bd84863" : {
         "desc" : "アドレス（住所・所在地）・ベース・レジストリの町字マスターデータセットです。",
         "file_name" : "mt_town_city382108.csv.zip",
         "length" : 3870,
         "mime" : "application/zip",
         "sha256" : "4fbdb8f6b6d17137a687c0cecbda07d1c7684e7aca5c9a182636a14b8394bde3",
         "time" : 1733982625,
         "title" : "愛媛県 伊予市 町字マスター データセット",
         "type" : "file",
         "url" : "https://catalog.registries.digital.go.jp/rsc/address/mt_town_city382108.csv.zip"
      },
      "file:id:f2585e3f-d8c1-4298-bbec-67c29f9d76b7" : {
         "desc" : "メタデータをXML形式でダウンロードします。",
         "file_name" : "ba-o1-382108_g2-000003.xml",
         "length" : 3404,
         "mime" : "application/rdf\u002Bxml",
         "sha256" : "355aae9779742efa1274290a654ca2695bdd96e29518b26f1372e13465e4073a",
         "time" : 1733982626,
         "title" : "メタデータ（詳細）",
         "type" : "file",
         "url" : "https://catalog.registries.digital.go.jp/rc/dataset/ba-o1-382108_g2-000003.xml"
      },
      "meta:activity.html" : {
         "desc" : "",
         "length" : 11977,
         "mime" : "text/html; charset=utf-8",
         "sha256" : "89a9c3e07397b88ad5299ece1f8954fc423994499124b723811eac0de1546820",
         "time" : 1733982624,
         "title" : "",
         "type" : "meta",
         "url" : "https://catalog.registries.digital.go.jp/rc/dataset/activity/ba-o1-382108_g2-000003"
      },
      "meta:ckan.json" : {
         "desc" : "",
         "length" : 5447,
         "mime" : "application/json;charset=utf-8",
         "sha256" : "fe7521afed165471e1caf9bce4bd5cc2bff1990c3bfe8b55cc2cc133f02f7595",
         "time" : 1720065390.57601,
         "title" : "愛媛県 伊予市 町字マスター データセット",
         "type" : "meta",
         "url" : "https://catalog.registries.digital.go.jp/rc/api/action/package_show?id=ba-o1-382108_g2-000003"
      }
   },
   "legal" : {
      "is_free" : "free",
      "legal" : [
         {
            "dir" : "ltr",
            "full_url" : "https://creativecommons.org/licenses/by/4.0/",
            "is_free" : "free",
            "key" : "CC-BY-4.0",
            "label" : "Creative Commons Attribution 4.0 International",
            "lang" : "en",
            "notice" : {
               "holder" : {
                  "dir" : "auto",
                  "lang" : "ja",
                  "value" : "デジタル庁",
                  "writing_mode" : "horizontal-tb"
               },
               "need_modified_flag" : 1,
               "title" : {
                  "dir" : "auto",
                  "lang" : "ja",
                  "value" : "愛媛県 伊予市 町字マスター データセット",
                  "writing_mode" : "horizontal-tb"
               },
               "url" : "https://catalog.registries.digital.go.jp/rc/dataset/ba-o1-382108_g2-000003"
            },
            "source_type" : "package",
            "source_url" : "https://catalog.registries.digital.go.jp/rc/api/action/package_show?id=ba-o1-382108_g2-000003",
            "type" : "license",
            "writing_mode" : "horizontal-tb"
         },
         {
            "alt" : [
               {
                  "dir" : "ltr",
                  "full_url" : "https://creativecommons.org/licenses/by/4.0/",
                  "is_free" : "free",
                  "key" : "CC-BY-4.0",
                  "label" : "Creative Commons Attribution 4.0 International",
                  "lang" : "en",
                  "notice" : {
                     "holder" : {
                        "dir" : "ltr",
                        "lang" : "ja",
                        "value" : "デジタル庁",
                        "writing_mode" : "horizontal-tb"
                     },
                     "need_modified_flag" : 1,
                     "title" : {
                        "dir" : "auto",
                        "lang" : "ja",
                        "value" : "愛媛県 伊予市 町字マスター データセット",
                        "writing_mode" : "horizontal-tb"
                     },
                     "url" : "https://catalog.registries.digital.go.jp/rc/dataset/ba-o1-382108_g2-000003"
                  },
                  "type" : "license",
                  "writing_mode" : "horizontal-tb"
               }
            ],
            "dir" : "ltr",
            "full_url" : "https://catalog.registries.digital.go.jp/rc/terms",
            "is_free" : "unknown",
            "key" : "-ddsd-terms-catalog.registries.digital.go.jp",
            "label" : "利用規約 - レジストリカタログ",
            "lang" : "ja",
            "notice" : {
               "holder" : {
                  "dir" : "ltr",
                  "lang" : "ja",
                  "value" : "デジタル庁",
                  "writing_mode" : "horizontal-tb"
               },
               "need_modified_flag" : 1,
               "template" : {
                  "dir" : "ltr",
                  "lang" : "ja",
                  "value" : "「{title}」（{holder}）（{url}）を加工して作成",
                  "writing_mode" : "horizontal-tb"
               },
               "template_not_modified" : {
                  "dir" : "ltr",
                  "lang" : "ja",
                  "value" : "レジストリカタログ（{url}）",
                  "writing_mode" : "horizontal-tb"
               },
               "title" : {
                  "dir" : "auto",
                  "lang" : "ja",
                  "value" : "愛媛県 伊予市 町字マスター データセット",
                  "writing_mode" : "horizontal-tb"
               },
               "url" : "https://catalog.registries.digital.go.jp/rc/dataset/ba-o1-382108_g2-000003"
            },
            "source_type" : "site",
            "source_url" : "https://catalog.registries.digital.go.jp/rc/terms",
            "type" : "site_terms",
            "writing_mode" : "horizontal-tb"
         },
         {
            "dir" : "ltr",
            "is_free" : "neutral",
            "key" : "-ddsd-disclaimer",
            "lang" : "ja",
            "notice" : {
               "template" : {
                  "dir" : "ltr",
                  "lang" : "ja",
                  "value" : "これらの法的な表示はソフトウェアにより機械的に抽出・生成したものです。ソフトウェアの制作者はその正確性、完全性、その他を一切保証しません。",
                  "writing_mode" : "horizontal-tb"
               }
            },
            "source_type" : "sniffer",
            "type" : "disclaimer",
            "writing_mode" : "horizontal-tb"
         }
      ]
   },
   "length" : 71091,
   "mirrorzip" : {
      "length" : 30931,
      "set" : "free-2",
      "sha256" : "0139ab1a86428ddef28826029f6b8fde2dffd51b1013b7e842425582743c35e6"
   },
   "package" : {
      "author" : "",
      "ckan_api_url" : "https://catalog.registries.digital.go.jp/rc/api/action/package_show?id=ba-o1-382108_g2-000003",
      "desc" : "アドレス（住所・所在地）・ベース・レジストリの町字マスターデータセットです。",
      "org" : "デジタル庁",
      "page_url" : "https://catalog.registries.digital.go.jp/rc/dataset/ba-o1-382108_g2-000003",
      "tags" : [
         "デジタル庁",
         "土地・地図",
         "住所情報",
         "市区町村",
         "都道府県"
      ],
      "time" : 1720065390.57601,
      "title" : "愛媛県 伊予市 町字マスター データセット"
   },
   "ref_key_text" : "6\u001C81de9f9c683ce7292b1097c2c9eda644cb0d56686169eedcb7da6e3dbfeb6d4a\u001Cfree\u001C0\u001C0"
}
