{
   "files" : {
      "file:id:5cbc0535-a2d0-48f2-95e2-d35846207018" : {
         "desc" : "ベース・レジストリ（アドレス）のリソース定義です。（外部サイトが開きます）",
         "file_name" : "base_registry_address",
         "length" : 62630,
         "mime" : "text/html; charset=utf-8",
         "sha256" : "dd9f419df6974cf5e894d42a17eed9d1089b46a8e3fcf203f0702a93457bcfb3",
         "time" : 1744176717,
         "title" : "リソース定義",
         "type" : "file",
         "url" : "https://www.digital.go.jp/policies/base_registry_address"
      },
      "file:id:ed9a1cae-0396-43a3-a84b-1a151328aa99" : {
         "desc" : "アドレス（住所・所在地）・ベース・レジストリの町字マスター位置参照拡張データセットです。",
         "file_name" : "mt_town_pos_city015717.csv.zip",
         "length" : 597,
         "mime" : "application/zip",
         "sha256" : "63ecb439d8a1c882474d1f0512c9cc894164b75e88c6339acd22c27bd44550c4",
         "time" : 1744176818,
         "title" : "北海道 虻田郡豊浦町 町字マスター位置参照拡張 データセット",
         "type" : "file",
         "url" : "https://catalog.registries.digital.go.jp/rsc/address/mt_town_pos_city015717.csv.zip"
      },
      "file:id:f415d27a-d9ea-4185-a370-4e263f3dea21" : {
         "desc" : "メタデータをXML形式でダウンロードします。",
         "file_name" : "ba-o1-015717_g2-000006.xml",
         "length" : 3525,
         "mime" : "application/rdf\u002Bxml",
         "sha256" : "be404fa3b770581a000b0345be81c3ba9f867c40c31e81edbcdfff1b54fdca72",
         "time" : 1744176819,
         "title" : "メタデータ（詳細）",
         "type" : "file",
         "url" : "https://catalog.registries.digital.go.jp/rc/dataset/ba-o1-015717_g2-000006.xml"
      },
      "meta:activity.html" : {
         "desc" : "",
         "length" : 11341,
         "mime" : "text/html; charset=utf-8",
         "sha256" : "9c93480c975c17f3eaeca97d5e99c0fd4a80b9565d8f69594a6f91c8aa8d437e",
         "time" : 1744176816,
         "title" : "",
         "type" : "meta",
         "url" : "https://catalog.registries.digital.go.jp/rc/dataset/activity/ba-o1-015717_g2-000006"
      },
      "meta:ckan.json" : {
         "desc" : "",
         "length" : 5673,
         "mime" : "application/json;charset=utf-8",
         "sha256" : "c1214e8de5898c1420d17074eb37a849e98bad8190879d70c2982a96cf277a83",
         "time" : 1710242870.65946,
         "title" : "北海道 虻田郡豊浦町 町字マスター位置参照拡張 データセット",
         "type" : "meta",
         "url" : "https://catalog.registries.digital.go.jp/rc/api/action/package_show?id=ba-o1-015717_g2-000006"
      }
   },
   "legal" : {
      "is_free" : "free",
      "legal" : [
         {
            "dir" : "ltr",
            "full_url" : "https://creativecommons.org/licenses/by/4.0/",
            "is_free" : "free",
            "key" : "CC-BY-4.0",
            "label" : "Creative Commons Attribution 4.0 International",
            "lang" : "en",
            "notice" : {
               "holder" : {
                  "dir" : "auto",
                  "lang" : "ja",
                  "value" : "北海道",
                  "writing_mode" : "horizontal-tb"
               },
               "need_modified_flag" : 1,
               "title" : {
                  "dir" : "auto",
                  "lang" : "ja",
                  "value" : "北海道 虻田郡豊浦町 町字マスター位置参照拡張 データセット",
                  "writing_mode" : "horizontal-tb"
               },
               "url" : "https://catalog.registries.digital.go.jp/rc/dataset/ba-o1-015717_g2-000006"
            },
            "source_type" : "package",
            "source_url" : "https://catalog.registries.digital.go.jp/rc/api/action/package_show?id=ba-o1-015717_g2-000006",
            "type" : "license",
            "writing_mode" : "horizontal-tb"
         },
         {
            "alt" : [
               {
                  "dir" : "ltr",
                  "full_url" : "https://creativecommons.org/licenses/by/4.0/",
                  "is_free" : "free",
                  "key" : "CC-BY-4.0",
                  "label" : "Creative Commons Attribution 4.0 International",
                  "lang" : "en",
                  "notice" : {
                     "holder" : {
                        "dir" : "ltr",
                        "lang" : "ja",
                        "value" : "デジタル庁",
                        "writing_mode" : "horizontal-tb"
                     },
                     "need_modified_flag" : 1,
                     "title" : {
                        "dir" : "auto",
                        "lang" : "ja",
                        "value" : "北海道 虻田郡豊浦町 町字マスター位置参照拡張 データセット",
                        "writing_mode" : "horizontal-tb"
                     },
                     "url" : "https://catalog.registries.digital.go.jp/rc/dataset/ba-o1-015717_g2-000006"
                  },
                  "type" : "license",
                  "writing_mode" : "horizontal-tb"
               }
            ],
            "dir" : "ltr",
            "full_url" : "https://catalog.registries.digital.go.jp/rc/terms",
            "is_free" : "unknown",
            "key" : "-ddsd-terms-catalog.registries.digital.go.jp",
            "label" : "利用規約 - レジストリカタログ",
            "lang" : "ja",
            "notice" : {
               "holder" : {
                  "dir" : "ltr",
                  "lang" : "ja",
                  "value" : "デジタル庁",
                  "writing_mode" : "horizontal-tb"
               },
               "need_modified_flag" : 1,
               "template" : {
                  "dir" : "ltr",
                  "lang" : "ja",
                  "value" : "「{title}」（{holder}）（{url}）を加工して作成",
                  "writing_mode" : "horizontal-tb"
               },
               "template_not_modified" : {
                  "dir" : "ltr",
                  "lang" : "ja",
                  "value" : "レジストリカタログ（{url}）",
                  "writing_mode" : "horizontal-tb"
               },
               "title" : {
                  "dir" : "auto",
                  "lang" : "ja",
                  "value" : "北海道 虻田郡豊浦町 町字マスター位置参照拡張 データセット",
                  "writing_mode" : "horizontal-tb"
               },
               "url" : "https://catalog.registries.digital.go.jp/rc/dataset/ba-o1-015717_g2-000006"
            },
            "source_type" : "site",
            "source_url" : "https://catalog.registries.digital.go.jp/rc/terms",
            "type" : "site_terms",
            "writing_mode" : "horizontal-tb"
         },
         {
            "dir" : "ltr",
            "is_free" : "neutral",
            "key" : "-ddsd-disclaimer",
            "lang" : "ja",
            "notice" : {
               "template" : {
                  "dir" : "ltr",
                  "lang" : "ja",
                  "value" : "これらの法的な表示はソフトウェアにより機械的に抽出・生成したものです。ソフトウェアの制作者はその正確性、完全性、その他を一切保証しません。",
                  "writing_mode" : "horizontal-tb"
               }
            },
            "source_type" : "sniffer",
            "type" : "disclaimer",
            "writing_mode" : "horizontal-tb"
         }
      ]
   },
   "length" : 83766,
   "mirrorzip" : {
      "length" : 30294,
      "set" : "free-4",
      "sha256" : "636194ec7b26154840965a628b2a236d17cbd2496e400b6fd7fb7b9fbe35fb33"
   },
   "package" : {
      "author" : "",
      "ckan_api_url" : "https://catalog.registries.digital.go.jp/rc/api/action/package_show?id=ba-o1-015717_g2-000006",
      "desc" : "アドレス（住所・所在地）・ベース・レジストリの町字マスター位置参照拡張データセットです。",
      "org" : "北海道",
      "page_url" : "https://catalog.registries.digital.go.jp/rc/dataset/ba-o1-015717_g2-000006",
      "tags" : [
         "北海道",
         "土地・地図",
         "住所情報",
         "市区町村",
         "都道府県"
      ],
      "time" : 1710242870.65946,
      "title" : "北海道 虻田郡豊浦町 町字マスター位置参照拡張 データセット"
   },
   "ref_key_text" : "6\u001C6f545f1d299ced8dd033aa00f922d34588e5c24b33eee11a2bdb591c93ca5a62\u001Cfree\u001C0\u001C0"
}
