{
   "files" : {
      "file:id:189604fb-147c-4c99-a3bf-660410ca192c" : {
         "desc" : "",
         "file_name" : "mt_parcel_city282090.csv.zip",
         "length" : 3238054,
         "mime" : "application/zip",
         "sha256" : "12a0ea8fddb14dff9154bd93039375b21ee641263af69d89155f0d9b2c7801f2",
         "time" : 1743744685,
         "title" : "兵庫県 豊岡市 地番マスター データセット",
         "type" : "file",
         "url" : "https://catalog.registries.digital.go.jp/rsc/address/mt_parcel_city282090.csv.zip"
      },
      "file:id:4d6b5ddc-4d5d-4f22-974a-dbecd717e1ef" : {
         "desc" : "",
         "file_name" : "ba-o1-282090_g2-000010.xml",
         "length" : 4068,
         "mime" : "application/rdf\u002Bxml",
         "sha256" : "fe08530c38658e2f44de1f577ba776c9aba0f19d6607862d5f4d3bdacf9b447d",
         "time" : 1743744693,
         "title" : "メタデータ（詳細）",
         "type" : "file",
         "url" : "https://catalog.registries.digital.go.jp/rc/dataset/ba-o1-282090_g2-000010.xml"
      },
      "file:id:dee08a62-89ff-42d4-9a13-77cb5dec5541" : {
         "desc" : "",
         "file_name" : "base_registry_address",
         "length" : 62630,
         "mime" : "text/html; charset=utf-8",
         "sha256" : "dd9f419df6974cf5e894d42a17eed9d1089b46a8e3fcf203f0702a93457bcfb3",
         "time" : 1743744664,
         "title" : "リソース定義",
         "type" : "file",
         "url" : "https://www.digital.go.jp/policies/base_registry_address"
      },
      "meta:activity.html" : {
         "desc" : "",
         "length" : 12730,
         "mime" : "text/html; charset=utf-8",
         "sha256" : "fa9f97124b47130bfccca3b60439ade46abfa0d153b92ef0bc760a5fade905b6",
         "time" : 1743744683,
         "title" : "",
         "type" : "meta",
         "url" : "https://catalog.registries.digital.go.jp/rc/dataset/activity/ba-o1-282090_g2-000010"
      },
      "meta:ckan.json" : {
         "desc" : "",
         "length" : 6633,
         "mime" : "application/json;charset=utf-8",
         "sha256" : "ede8872be358985ea21f8bea45ea93c55584b0da56049aefff641db59900cb44",
         "time" : 1714149075.18881,
         "title" : "兵庫県 豊岡市 地番マスター データセット",
         "type" : "meta",
         "url" : "https://catalog.registries.digital.go.jp/rc/api/action/package_show?id=ba-o1-282090_g2-000010"
      }
   },
   "legal" : {
      "is_free" : "unknown",
      "legal" : [
         {
            "dir" : "ltr",
            "full_url" : "https://creativecommons.org/licenses/by/4.0/",
            "is_free" : "free",
            "key" : "CC-BY-4.0",
            "label" : "Creative Commons Attribution 4.0 International",
            "lang" : "en",
            "notice" : {
               "holder" : {
                  "dir" : "auto",
                  "lang" : "ja",
                  "value" : "兵庫県",
                  "writing_mode" : "horizontal-tb"
               },
               "need_modified_flag" : 1,
               "title" : {
                  "dir" : "auto",
                  "lang" : "ja",
                  "value" : "兵庫県 豊岡市 地番マスター データセット",
                  "writing_mode" : "horizontal-tb"
               },
               "url" : "https://catalog.registries.digital.go.jp/rc/dataset/ba-o1-282090_g2-000010"
            },
            "source_type" : "package",
            "source_url" : "https://catalog.registries.digital.go.jp/rc/api/action/package_show?id=ba-o1-282090_g2-000010",
            "type" : "license",
            "writing_mode" : "horizontal-tb"
         },
         {
            "dir" : "auto",
            "extracted_url" : "https://www.digital.go.jp/policies/base_registry_address_tos",
            "is_free" : "unknown",
            "key" : "-ddsd-unknown",
            "lang" : "ja",
            "notes" : "アドレス（住所・所在地）ベース・レジストリの地番マスターデータセットです。地番マスターは「登記所備付地図データ」（法務省）を加工してデジタル庁で作成しています。コンテンツ利用に当たっては、[アドレス・ベース・レジストリの利用規約](https://www.digital.go.jp/policies/base_registry_address_tos)に同意したものとみなします。",
            "source_type" : "site",
            "source_url" : "https://www.digital.go.jp/policies/base_registry_address_tos",
            "type" : "site_terms",
            "writing_mode" : "horizontal-tb"
         },
         {
            "dir" : "auto",
            "extracted_url" : "https://www.geospatial.jp/ckan/dataset/houmusyouchizu-riyoukiyaku/resource/47871bf1-4c85-48f7-a8fe-b27c6643c1c5",
            "is_free" : "unknown",
            "key" : "-ddsd-ckan-package",
            "lang" : "ja",
            "notes" : "アドレス（住所・所在地）ベース・レジストリの地番マスターデータセットです。地番マスターは「登記所備付地図データ」（法務省）を加工してデジタル庁で作成しています。コンテンツ利用に当たっては、[アドレス・ベース・レジストリの利用規約](https://www.digital.go.jp/policies/base_registry_address_tos)に同意したものとみなします。",
            "source_type" : "package",
            "source_url" : "https://catalog.registries.digital.go.jp/rc/api/action/package_show?id=ba-o1-282090_g2-000010",
            "type" : "license",
            "writing_mode" : "horizontal-tb"
         },
         {
            "alt" : [
               {
                  "dir" : "ltr",
                  "full_url" : "https://creativecommons.org/licenses/by/4.0/",
                  "is_free" : "free",
                  "key" : "CC-BY-4.0",
                  "label" : "Creative Commons Attribution 4.0 International",
                  "lang" : "en",
                  "notice" : {
                     "holder" : {
                        "dir" : "ltr",
                        "lang" : "ja",
                        "value" : "デジタル庁",
                        "writing_mode" : "horizontal-tb"
                     },
                     "need_modified_flag" : 1,
                     "title" : {
                        "dir" : "auto",
                        "lang" : "ja",
                        "value" : "兵庫県 豊岡市 地番マスター データセット",
                        "writing_mode" : "horizontal-tb"
                     },
                     "url" : "https://catalog.registries.digital.go.jp/rc/dataset/ba-o1-282090_g2-000010"
                  },
                  "type" : "license",
                  "writing_mode" : "horizontal-tb"
               }
            ],
            "dir" : "ltr",
            "full_url" : "https://catalog.registries.digital.go.jp/rc/terms",
            "is_free" : "unknown",
            "key" : "-ddsd-terms-catalog.registries.digital.go.jp",
            "label" : "利用規約 - レジストリカタログ",
            "lang" : "ja",
            "notice" : {
               "holder" : {
                  "dir" : "ltr",
                  "lang" : "ja",
                  "value" : "デジタル庁",
                  "writing_mode" : "horizontal-tb"
               },
               "need_modified_flag" : 1,
               "template" : {
                  "dir" : "ltr",
                  "lang" : "ja",
                  "value" : "「{title}」（{holder}）（{url}）を加工して作成",
                  "writing_mode" : "horizontal-tb"
               },
               "template_not_modified" : {
                  "dir" : "ltr",
                  "lang" : "ja",
                  "value" : "レジストリカタログ（{url}）",
                  "writing_mode" : "horizontal-tb"
               },
               "title" : {
                  "dir" : "auto",
                  "lang" : "ja",
                  "value" : "兵庫県 豊岡市 地番マスター データセット",
                  "writing_mode" : "horizontal-tb"
               },
               "url" : "https://catalog.registries.digital.go.jp/rc/dataset/ba-o1-282090_g2-000010"
            },
            "source_type" : "site",
            "source_url" : "https://catalog.registries.digital.go.jp/rc/terms",
            "type" : "site_terms",
            "writing_mode" : "horizontal-tb"
         },
         {
            "dir" : "ltr",
            "is_free" : "neutral",
            "key" : "-ddsd-disclaimer",
            "lang" : "ja",
            "notice" : {
               "template" : {
                  "dir" : "ltr",
                  "lang" : "ja",
                  "value" : "これらの法的な表示はソフトウェアにより機械的に抽出・生成したものです。ソフトウェアの制作者はその正確性、完全性、その他を一切保証しません。",
                  "writing_mode" : "horizontal-tb"
               }
            },
            "source_type" : "sniffer",
            "type" : "disclaimer",
            "writing_mode" : "horizontal-tb"
         }
      ]
   },
   "length" : 3324115,
   "mirrorzip" : {
      "length" : 3066281,
      "set" : "nonfree-3",
      "sha256" : "2e07096603d9c9c9a5bd4dc13f2a4757ac98428530f0d2fe43aa654d733fbe4a"
   },
   "package" : {
      "author" : "",
      "ckan_api_url" : "https://catalog.registries.digital.go.jp/rc/api/action/package_show?id=ba-o1-282090_g2-000010",
      "desc" : "",
      "org" : "兵庫県",
      "page_url" : "https://catalog.registries.digital.go.jp/rc/dataset/ba-o1-282090_g2-000010",
      "tags" : [
         "兵庫県",
         "土地・地図",
         "住所情報",
         "市区町村",
         "都道府県"
      ],
      "time" : 1714149075.18881,
      "title" : "兵庫県 豊岡市 地番マスター データセット"
   },
   "ref_key_text" : "6\u001C5fdf4e2693f65e74afc84bf78fd39694251e8dd48db20adb93b218d9eadc41af\u001Cunknown\u001C0\u001C0"
}
