{
   "files" : {
      "file:id:2a234c08-2940-403d-a525-030dc3e2c7bd" : {
         "desc" : "ベース・レジストリ（アドレス）のリソース定義です。（外部サイトが開きます）",
         "file_name" : "base_registry_address",
         "length" : 46393,
         "mime" : "text/html; charset=utf-8",
         "sha256" : "04eaa48795c92a024dd9de62c9599d5f7215ebbf3bc99cb88dc06dff450191ca",
         "time" : 1733952332,
         "title" : "リソース定義",
         "type" : "file",
         "url" : "https://www.digital.go.jp/policies/base_registry_address"
      },
      "file:id:34586d08-0999-46ba-b8bb-30eb823d546f" : {
         "desc" : "メタデータをXML形式でダウンロードします。",
         "file_name" : "ba-o1-114651_g2-000003.xml",
         "length" : 3440,
         "mime" : "application/rdf\u002Bxml",
         "sha256" : "3a97a887511b2db4df6dece5268504dc5eacecf6966edb3fbbb576d2d39b9ffe",
         "time" : 1733982543,
         "title" : "メタデータ（詳細）",
         "type" : "file",
         "url" : "https://catalog.registries.digital.go.jp/rc/dataset/ba-o1-114651_g2-000003.xml"
      },
      "file:id:7a6ee4d1-0398-417f-9400-e57626acb185" : {
         "desc" : "アドレス（住所・所在地）・ベース・レジストリの町字マスターデータセットです。",
         "file_name" : "mt_town_city114651.csv.zip",
         "length" : 2004,
         "mime" : "application/zip",
         "sha256" : "948c5279f86bb0e3632286538808222df97cdc72a292f2a4559710e83fcf360a",
         "time" : 1733982542,
         "title" : "埼玉県 北葛飾郡松伏町 町字マスター データセット",
         "type" : "file",
         "url" : "https://catalog.registries.digital.go.jp/rsc/address/mt_town_city114651.csv.zip"
      },
      "meta:activity.html" : {
         "desc" : "",
         "length" : 12085,
         "mime" : "text/html; charset=utf-8",
         "sha256" : "90a3e4d297ffa4a871e9a1ad6570d45d6ec4b57e2c99ed332cb41d4504dca1a7",
         "time" : 1733982540,
         "title" : "",
         "type" : "meta",
         "url" : "https://catalog.registries.digital.go.jp/rc/dataset/activity/ba-o1-114651_g2-000003"
      },
      "meta:ckan.json" : {
         "desc" : "",
         "length" : 5519,
         "mime" : "application/json;charset=utf-8",
         "sha256" : "4e5656027fb5924ee7c54230d74cf289a511e62d070332e0b3338803ad52306c",
         "time" : 1719992892.13435,
         "title" : "埼玉県 北葛飾郡松伏町 町字マスター データセット",
         "type" : "meta",
         "url" : "https://catalog.registries.digital.go.jp/rc/api/action/package_show?id=ba-o1-114651_g2-000003"
      }
   },
   "legal" : {
      "is_free" : "free",
      "legal" : [
         {
            "dir" : "ltr",
            "full_url" : "https://creativecommons.org/licenses/by/4.0/",
            "is_free" : "free",
            "key" : "CC-BY-4.0",
            "label" : "Creative Commons Attribution 4.0 International",
            "lang" : "en",
            "notice" : {
               "holder" : {
                  "dir" : "auto",
                  "lang" : "ja",
                  "value" : "デジタル庁",
                  "writing_mode" : "horizontal-tb"
               },
               "need_modified_flag" : 1,
               "title" : {
                  "dir" : "auto",
                  "lang" : "ja",
                  "value" : "埼玉県 北葛飾郡松伏町 町字マスター データセット",
                  "writing_mode" : "horizontal-tb"
               },
               "url" : "https://catalog.registries.digital.go.jp/rc/dataset/ba-o1-114651_g2-000003"
            },
            "source_type" : "package",
            "source_url" : "https://catalog.registries.digital.go.jp/rc/api/action/package_show?id=ba-o1-114651_g2-000003",
            "type" : "license",
            "writing_mode" : "horizontal-tb"
         },
         {
            "alt" : [
               {
                  "dir" : "ltr",
                  "full_url" : "https://creativecommons.org/licenses/by/4.0/",
                  "is_free" : "free",
                  "key" : "CC-BY-4.0",
                  "label" : "Creative Commons Attribution 4.0 International",
                  "lang" : "en",
                  "notice" : {
                     "holder" : {
                        "dir" : "ltr",
                        "lang" : "ja",
                        "value" : "デジタル庁",
                        "writing_mode" : "horizontal-tb"
                     },
                     "need_modified_flag" : 1,
                     "title" : {
                        "dir" : "auto",
                        "lang" : "ja",
                        "value" : "埼玉県 北葛飾郡松伏町 町字マスター データセット",
                        "writing_mode" : "horizontal-tb"
                     },
                     "url" : "https://catalog.registries.digital.go.jp/rc/dataset/ba-o1-114651_g2-000003"
                  },
                  "type" : "license",
                  "writing_mode" : "horizontal-tb"
               }
            ],
            "dir" : "ltr",
            "full_url" : "https://catalog.registries.digital.go.jp/rc/terms",
            "is_free" : "unknown",
            "key" : "-ddsd-terms-catalog.registries.digital.go.jp",
            "label" : "利用規約 - レジストリカタログ",
            "lang" : "ja",
            "notice" : {
               "holder" : {
                  "dir" : "ltr",
                  "lang" : "ja",
                  "value" : "デジタル庁",
                  "writing_mode" : "horizontal-tb"
               },
               "need_modified_flag" : 1,
               "template" : {
                  "dir" : "ltr",
                  "lang" : "ja",
                  "value" : "「{title}」（{holder}）（{url}）を加工して作成",
                  "writing_mode" : "horizontal-tb"
               },
               "template_not_modified" : {
                  "dir" : "ltr",
                  "lang" : "ja",
                  "value" : "レジストリカタログ（{url}）",
                  "writing_mode" : "horizontal-tb"
               },
               "title" : {
                  "dir" : "auto",
                  "lang" : "ja",
                  "value" : "埼玉県 北葛飾郡松伏町 町字マスター データセット",
                  "writing_mode" : "horizontal-tb"
               },
               "url" : "https://catalog.registries.digital.go.jp/rc/dataset/ba-o1-114651_g2-000003"
            },
            "source_type" : "site",
            "source_url" : "https://catalog.registries.digital.go.jp/rc/terms",
            "type" : "site_terms",
            "writing_mode" : "horizontal-tb"
         },
         {
            "dir" : "ltr",
            "is_free" : "neutral",
            "key" : "-ddsd-disclaimer",
            "lang" : "ja",
            "notice" : {
               "template" : {
                  "dir" : "ltr",
                  "lang" : "ja",
                  "value" : "これらの法的な表示はソフトウェアにより機械的に抽出・生成したものです。ソフトウェアの制作者はその正確性、完全性、その他を一切保証しません。",
                  "writing_mode" : "horizontal-tb"
               }
            },
            "source_type" : "sniffer",
            "type" : "disclaimer",
            "writing_mode" : "horizontal-tb"
         }
      ]
   },
   "length" : 69441,
   "mirrorzip" : {
      "length" : 29138,
      "set" : "free-2",
      "sha256" : "e9f2a9b19b8844823afc69d3a8a56b1800a49affcd307a223026f788af2d7e90"
   },
   "package" : {
      "author" : "",
      "ckan_api_url" : "https://catalog.registries.digital.go.jp/rc/api/action/package_show?id=ba-o1-114651_g2-000003",
      "desc" : "アドレス（住所・所在地）・ベース・レジストリの町字マスターデータセットです。",
      "org" : "デジタル庁",
      "page_url" : "https://catalog.registries.digital.go.jp/rc/dataset/ba-o1-114651_g2-000003",
      "tags" : [
         "デジタル庁",
         "土地・地図",
         "住所情報",
         "市区町村",
         "都道府県"
      ],
      "time" : 1719992892.13435,
      "title" : "埼玉県 北葛飾郡松伏町 町字マスター データセット"
   },
   "ref_key_text" : "6\u001Cd4d635c5a1219cd810b2c53afebf8afa0470a9216562c4b12335b793a3b58d8d\u001Cfree\u001C0\u001C0"
}
