{
   "files" : {
      "file:id:9ad1d823-d90e-4925-8b7e-c90b0d48c266" : {
         "desc" : "メタデータをXML形式でダウンロードします。",
         "file_name" : "ba-o1-202029_g2-000004.xml",
         "length" : 3476,
         "mime" : "application/rdf\u002Bxml",
         "sha256" : "13de0af0c887be59988639adf910f33a01bcfe7b1447012f2773d237bff0eece",
         "time" : 1742246977,
         "title" : "メタデータ（詳細）",
         "type" : "file",
         "url" : "https://catalog.registries.digital.go.jp/rc/dataset/ba-o1-202029_g2-000004.xml"
      },
      "file:id:d9625e59-589b-4354-bd60-5f0b5524d705" : {
         "desc" : "ベース・レジストリ（アドレス）のリソース定義です。（外部サイトが開きます）",
         "file_name" : "base_registry_address",
         "length" : 63085,
         "mime" : "text/html; charset=utf-8",
         "sha256" : "bf245da72aa16c00f4a85c7e37aba6a311b4f030a21fc1dcb6ffaf7efa109e35",
         "time" : 1742218684,
         "title" : "リソース定義",
         "type" : "file",
         "url" : "https://www.digital.go.jp/policies/base_registry_address"
      },
      "file:id:e609ab01-735d-46f4-9b84-4a3f92438918" : {
         "desc" : "アドレス（住所・所在地）・ベース・レジストリの住居表示-街区マスターデータセットです。",
         "file_name" : "mt_rsdtdsp_blk_city202029.csv.zip",
         "length" : 18605,
         "mime" : "application/zip",
         "sha256" : "78f61ad223b0e311cfcfa856c098f76e70ddcc535b0d4c4228edc2eca9f23bed",
         "time" : 1742246976,
         "title" : "長野県 松本市 住居表示-街区マスター データセット",
         "type" : "file",
         "url" : "https://catalog.registries.digital.go.jp/rsc/address/mt_rsdtdsp_blk_city202029.csv.zip"
      },
      "meta:activity.html" : {
         "desc" : "",
         "length" : 11230,
         "mime" : "text/html; charset=utf-8",
         "sha256" : "5d6c3dc5bb54f8bd4a11762850dedccf0dd7d9c058ddc9f603e3d1daf6cf264d",
         "time" : 1742246974,
         "title" : "",
         "type" : "meta",
         "url" : "https://catalog.registries.digital.go.jp/rc/dataset/activity/ba-o1-202029_g2-000004"
      },
      "meta:ckan.json" : {
         "desc" : "",
         "length" : 5567,
         "mime" : "application/json;charset=utf-8",
         "sha256" : "f6e585f558be46b1ea185fecf139d639981524b12dc2b89ab3dd7161f5756513",
         "time" : 1710278922.80355,
         "title" : "長野県 松本市 住居表示-街区マスター データセット",
         "type" : "meta",
         "url" : "https://catalog.registries.digital.go.jp/rc/api/action/package_show?id=ba-o1-202029_g2-000004"
      }
   },
   "legal" : {
      "is_free" : "free",
      "legal" : [
         {
            "dir" : "ltr",
            "full_url" : "https://creativecommons.org/licenses/by/4.0/",
            "is_free" : "free",
            "key" : "CC-BY-4.0",
            "label" : "Creative Commons Attribution 4.0 International",
            "lang" : "en",
            "notice" : {
               "holder" : {
                  "dir" : "auto",
                  "lang" : "ja",
                  "value" : "長野県",
                  "writing_mode" : "horizontal-tb"
               },
               "need_modified_flag" : 1,
               "title" : {
                  "dir" : "auto",
                  "lang" : "ja",
                  "value" : "長野県 松本市 住居表示-街区マスター データセット",
                  "writing_mode" : "horizontal-tb"
               },
               "url" : "https://catalog.registries.digital.go.jp/rc/dataset/ba-o1-202029_g2-000004"
            },
            "source_type" : "package",
            "source_url" : "https://catalog.registries.digital.go.jp/rc/api/action/package_show?id=ba-o1-202029_g2-000004",
            "type" : "license",
            "writing_mode" : "horizontal-tb"
         },
         {
            "alt" : [
               {
                  "dir" : "ltr",
                  "full_url" : "https://creativecommons.org/licenses/by/4.0/",
                  "is_free" : "free",
                  "key" : "CC-BY-4.0",
                  "label" : "Creative Commons Attribution 4.0 International",
                  "lang" : "en",
                  "notice" : {
                     "holder" : {
                        "dir" : "ltr",
                        "lang" : "ja",
                        "value" : "デジタル庁",
                        "writing_mode" : "horizontal-tb"
                     },
                     "need_modified_flag" : 1,
                     "title" : {
                        "dir" : "auto",
                        "lang" : "ja",
                        "value" : "長野県 松本市 住居表示-街区マスター データセット",
                        "writing_mode" : "horizontal-tb"
                     },
                     "url" : "https://catalog.registries.digital.go.jp/rc/dataset/ba-o1-202029_g2-000004"
                  },
                  "type" : "license",
                  "writing_mode" : "horizontal-tb"
               }
            ],
            "dir" : "ltr",
            "full_url" : "https://catalog.registries.digital.go.jp/rc/terms",
            "is_free" : "unknown",
            "key" : "-ddsd-terms-catalog.registries.digital.go.jp",
            "label" : "利用規約 - レジストリカタログ",
            "lang" : "ja",
            "notice" : {
               "holder" : {
                  "dir" : "ltr",
                  "lang" : "ja",
                  "value" : "デジタル庁",
                  "writing_mode" : "horizontal-tb"
               },
               "need_modified_flag" : 1,
               "template" : {
                  "dir" : "ltr",
                  "lang" : "ja",
                  "value" : "「{title}」（{holder}）（{url}）を加工して作成",
                  "writing_mode" : "horizontal-tb"
               },
               "template_not_modified" : {
                  "dir" : "ltr",
                  "lang" : "ja",
                  "value" : "レジストリカタログ（{url}）",
                  "writing_mode" : "horizontal-tb"
               },
               "title" : {
                  "dir" : "auto",
                  "lang" : "ja",
                  "value" : "長野県 松本市 住居表示-街区マスター データセット",
                  "writing_mode" : "horizontal-tb"
               },
               "url" : "https://catalog.registries.digital.go.jp/rc/dataset/ba-o1-202029_g2-000004"
            },
            "source_type" : "site",
            "source_url" : "https://catalog.registries.digital.go.jp/rc/terms",
            "type" : "site_terms",
            "writing_mode" : "horizontal-tb"
         },
         {
            "dir" : "ltr",
            "is_free" : "neutral",
            "key" : "-ddsd-disclaimer",
            "lang" : "ja",
            "notice" : {
               "template" : {
                  "dir" : "ltr",
                  "lang" : "ja",
                  "value" : "これらの法的な表示はソフトウェアにより機械的に抽出・生成したものです。ソフトウェアの制作者はその正確性、完全性、その他を一切保証しません。",
                  "writing_mode" : "horizontal-tb"
               }
            },
            "source_type" : "sniffer",
            "type" : "disclaimer",
            "writing_mode" : "horizontal-tb"
         }
      ]
   },
   "length" : 101963,
   "mirrorzip" : {
      "length" : 45965,
      "set" : "free-3",
      "sha256" : "ba16249b242003cbd6b84df05ba0c836f149a604e9aef8bdc873e6c78cb85ddd"
   },
   "package" : {
      "author" : "",
      "ckan_api_url" : "https://catalog.registries.digital.go.jp/rc/api/action/package_show?id=ba-o1-202029_g2-000004",
      "desc" : "アドレス（住所・所在地）・ベース・レジストリの住居表示-街区マスターデータセットです。",
      "org" : "長野県",
      "page_url" : "https://catalog.registries.digital.go.jp/rc/dataset/ba-o1-202029_g2-000004",
      "tags" : [
         "長野県",
         "土地・地図",
         "住所情報",
         "市区町村",
         "都道府県"
      ],
      "time" : 1710278922.80355,
      "title" : "長野県 松本市 住居表示-街区マスター データセット"
   },
   "ref_key_text" : "6\u001Ceb71e357ade2417be59d72532b29973ec828e7022c43470e95ad5ee69762879a\u001Cfree\u001C0\u001C0"
}
