{
   "files" : {
      "file:id:2735d17d-20ca-4287-ba44-b788ecf636ee" : {
         "desc" : "",
         "file_name" : "ba-o1-202088_g2-000010.xml",
         "length" : 4068,
         "mime" : "application/rdf\u002Bxml",
         "sha256" : "4169e242aec485b0ea7d660027143d9972e8182c5b38b89763a3bd015ad8d15d",
         "time" : 1741613849,
         "title" : "メタデータ（詳細）",
         "type" : "file",
         "url" : "https://catalog.registries.digital.go.jp/rc/dataset/ba-o1-202088_g2-000010.xml"
      },
      "file:id:2d7a58a7-a290-43c2-a86d-d536b9e1bf2f" : {
         "desc" : "",
         "file_name" : "base_registry_address",
         "length" : 63067,
         "mime" : "text/html; charset=utf-8",
         "sha256" : "590418db607a351db6b68fe5f3aeb7bb21622013ac0b77373f8cf3213b6304ec",
         "time" : 1741613794,
         "title" : "リソース定義",
         "type" : "file",
         "url" : "https://www.digital.go.jp/policies/base_registry_address"
      },
      "file:id:2f76bc66-d5fd-4dc1-9ff7-28828cc0ac4e" : {
         "desc" : "",
         "file_name" : "mt_parcel_city202088.csv.zip",
         "length" : 835543,
         "mime" : "application/zip",
         "sha256" : "48b6b53cd87b0b09f023b961b146c459f64524409f10a9f2c5802d7a942cefc4",
         "time" : 1741613848,
         "title" : "長野県 小諸市 地番マスター データセット",
         "type" : "file",
         "url" : "https://catalog.registries.digital.go.jp/rsc/address/mt_parcel_city202088.csv.zip"
      },
      "meta:activity.html" : {
         "desc" : "",
         "length" : 12730,
         "mime" : "text/html; charset=utf-8",
         "sha256" : "5d6815a37d9748339716f650f7b5b0f5232afa407012f2ac8582e539106bd99e",
         "time" : 1741613846,
         "title" : "",
         "type" : "meta",
         "url" : "https://catalog.registries.digital.go.jp/rc/dataset/activity/ba-o1-202088_g2-000010"
      },
      "meta:ckan.json" : {
         "desc" : "",
         "length" : 6633,
         "mime" : "application/json;charset=utf-8",
         "sha256" : "04323ecbbb251892d459d52a62c0ba57de05ff460e057e82c67c32b9dc31aca1",
         "time" : 1714144403.43831,
         "title" : "長野県 小諸市 地番マスター データセット",
         "type" : "meta",
         "url" : "https://catalog.registries.digital.go.jp/rc/api/action/package_show?id=ba-o1-202088_g2-000010"
      }
   },
   "legal" : {
      "is_free" : "unknown",
      "legal" : [
         {
            "dir" : "ltr",
            "full_url" : "https://creativecommons.org/licenses/by/4.0/",
            "is_free" : "free",
            "key" : "CC-BY-4.0",
            "label" : "Creative Commons Attribution 4.0 International",
            "lang" : "en",
            "notice" : {
               "holder" : {
                  "dir" : "auto",
                  "lang" : "ja",
                  "value" : "長野県",
                  "writing_mode" : "horizontal-tb"
               },
               "need_modified_flag" : 1,
               "title" : {
                  "dir" : "auto",
                  "lang" : "ja",
                  "value" : "長野県 小諸市 地番マスター データセット",
                  "writing_mode" : "horizontal-tb"
               },
               "url" : "https://catalog.registries.digital.go.jp/rc/dataset/ba-o1-202088_g2-000010"
            },
            "source_type" : "package",
            "source_url" : "https://catalog.registries.digital.go.jp/rc/api/action/package_show?id=ba-o1-202088_g2-000010",
            "type" : "license",
            "writing_mode" : "horizontal-tb"
         },
         {
            "dir" : "auto",
            "extracted_url" : "https://www.digital.go.jp/policies/base_registry_address_tos",
            "is_free" : "unknown",
            "key" : "-ddsd-unknown",
            "lang" : "ja",
            "notes" : "アドレス（住所・所在地）ベース・レジストリの地番マスターデータセットです。地番マスターは「登記所備付地図データ」（法務省）を加工してデジタル庁で作成しています。コンテンツ利用に当たっては、[アドレス・ベース・レジストリの利用規約](https://www.digital.go.jp/policies/base_registry_address_tos)に同意したものとみなします。",
            "source_type" : "site",
            "source_url" : "https://www.digital.go.jp/policies/base_registry_address_tos",
            "type" : "site_terms",
            "writing_mode" : "horizontal-tb"
         },
         {
            "dir" : "auto",
            "extracted_url" : "https://www.geospatial.jp/ckan/dataset/houmusyouchizu-riyoukiyaku/resource/47871bf1-4c85-48f7-a8fe-b27c6643c1c5",
            "is_free" : "unknown",
            "key" : "-ddsd-ckan-package",
            "lang" : "ja",
            "notes" : "アドレス（住所・所在地）ベース・レジストリの地番マスターデータセットです。地番マスターは「登記所備付地図データ」（法務省）を加工してデジタル庁で作成しています。コンテンツ利用に当たっては、[アドレス・ベース・レジストリの利用規約](https://www.digital.go.jp/policies/base_registry_address_tos)に同意したものとみなします。",
            "source_type" : "package",
            "source_url" : "https://catalog.registries.digital.go.jp/rc/api/action/package_show?id=ba-o1-202088_g2-000010",
            "type" : "license",
            "writing_mode" : "horizontal-tb"
         },
         {
            "alt" : [
               {
                  "dir" : "ltr",
                  "full_url" : "https://creativecommons.org/licenses/by/4.0/",
                  "is_free" : "free",
                  "key" : "CC-BY-4.0",
                  "label" : "Creative Commons Attribution 4.0 International",
                  "lang" : "en",
                  "notice" : {
                     "holder" : {
                        "dir" : "ltr",
                        "lang" : "ja",
                        "value" : "デジタル庁",
                        "writing_mode" : "horizontal-tb"
                     },
                     "need_modified_flag" : 1,
                     "title" : {
                        "dir" : "auto",
                        "lang" : "ja",
                        "value" : "長野県 小諸市 地番マスター データセット",
                        "writing_mode" : "horizontal-tb"
                     },
                     "url" : "https://catalog.registries.digital.go.jp/rc/dataset/ba-o1-202088_g2-000010"
                  },
                  "type" : "license",
                  "writing_mode" : "horizontal-tb"
               }
            ],
            "dir" : "ltr",
            "full_url" : "https://catalog.registries.digital.go.jp/rc/terms",
            "is_free" : "unknown",
            "key" : "-ddsd-terms-catalog.registries.digital.go.jp",
            "label" : "利用規約 - レジストリカタログ",
            "lang" : "ja",
            "notice" : {
               "holder" : {
                  "dir" : "ltr",
                  "lang" : "ja",
                  "value" : "デジタル庁",
                  "writing_mode" : "horizontal-tb"
               },
               "need_modified_flag" : 1,
               "template" : {
                  "dir" : "ltr",
                  "lang" : "ja",
                  "value" : "「{title}」（{holder}）（{url}）を加工して作成",
                  "writing_mode" : "horizontal-tb"
               },
               "template_not_modified" : {
                  "dir" : "ltr",
                  "lang" : "ja",
                  "value" : "レジストリカタログ（{url}）",
                  "writing_mode" : "horizontal-tb"
               },
               "title" : {
                  "dir" : "auto",
                  "lang" : "ja",
                  "value" : "長野県 小諸市 地番マスター データセット",
                  "writing_mode" : "horizontal-tb"
               },
               "url" : "https://catalog.registries.digital.go.jp/rc/dataset/ba-o1-202088_g2-000010"
            },
            "source_type" : "site",
            "source_url" : "https://catalog.registries.digital.go.jp/rc/terms",
            "type" : "site_terms",
            "writing_mode" : "horizontal-tb"
         },
         {
            "dir" : "ltr",
            "is_free" : "neutral",
            "key" : "-ddsd-disclaimer",
            "lang" : "ja",
            "notice" : {
               "template" : {
                  "dir" : "ltr",
                  "lang" : "ja",
                  "value" : "これらの法的な表示はソフトウェアにより機械的に抽出・生成したものです。ソフトウェアの制作者はその正確性、完全性、その他を一切保証しません。",
                  "writing_mode" : "horizontal-tb"
               }
            },
            "source_type" : "sniffer",
            "type" : "disclaimer",
            "writing_mode" : "horizontal-tb"
         }
      ]
   },
   "length" : 922041,
   "mirrorzip" : {
      "length" : 777125,
      "set" : "nonfree-3",
      "sha256" : "d02b569d6e81077d79125b237ef63276f899c44f0ea7e7661a38e5666ec5c10f"
   },
   "package" : {
      "author" : "",
      "ckan_api_url" : "https://catalog.registries.digital.go.jp/rc/api/action/package_show?id=ba-o1-202088_g2-000010",
      "desc" : "",
      "org" : "長野県",
      "page_url" : "https://catalog.registries.digital.go.jp/rc/dataset/ba-o1-202088_g2-000010",
      "tags" : [
         "長野県",
         "土地・地図",
         "住所情報",
         "市区町村",
         "都道府県"
      ],
      "time" : 1714144403.43831,
      "title" : "長野県 小諸市 地番マスター データセット"
   },
   "ref_key_text" : "6\u001Cd8afdeb43ca2f8039283d69445a497f3c71641f9d152a75bdcedd8c9b0c44798\u001Cunknown\u001C0\u001C0"
}
