{
   "files" : {
      "file:id:e92017a8-cffe-4fc2-a41d-dd582b46db22" : {
         "desc" : "",
         "file_name" : "jinkosetai-dotai.csv",
         "length" : 2657,
         "mime" : "text/csv",
         "sha256" : "249f88e5656ec094851d22e7460059a1d083de85d6afd9c72a72d5c9f60a62fb",
         "time" : 1740491174,
         "title" : "人口動態（昭和22年から令和6年）",
         "type" : "file",
         "url" : "https://www.city.yokohama.lg.jp/city-info/yokohamashi/tokei-chosa/portal/opendata/jinko-dotai.files/jinkosetai-dotai.csv"
      },
      "meta:activity.html" : {
         "desc" : "",
         "length" : 16616,
         "mime" : "text/html; charset=utf-8",
         "sha256" : "ca57c40385b78f8a765f22c8c82ae0b435b8ab5b3a722464afc6fe4b3c27b880",
         "time" : 1740491173,
         "title" : "",
         "type" : "meta",
         "url" : "https://data.city.yokohama.lg.jp/dataset/activity/seisaku_jinko-dotai"
      },
      "meta:ckan.json" : {
         "desc" : "",
         "length" : 2853,
         "mime" : "application/json;charset=utf-8",
         "sha256" : "38f4644b6c0ddabc8d39919f8c2796ed15c40c1ad6a460f68b921bfdba8eff64",
         "time" : 1738890283.49873,
         "title" : "人口動態（年次）",
         "type" : "meta",
         "url" : "https://data.city.yokohama.lg.jp/api/action/package_show?id=seisaku_jinko-dotai"
      }
   },
   "legal" : {
      "is_free" : "free",
      "legal" : [
         {
            "desc_url" : "https://opendefinition.org/licenses/cc-by/",
            "dir" : "ltr",
            "is_free" : "free",
            "key" : "-ddsd-cc-by",
            "label" : "Creative Commons Attribution",
            "lang" : "en",
            "notice" : {
               "holder" : {
                  "dir" : "auto",
                  "lang" : "ja",
                  "value" : "統計情報課 (政策経営局)",
                  "writing_mode" : "horizontal-tb"
               },
               "need_modified_flag" : 1,
               "title" : {
                  "dir" : "auto",
                  "lang" : "ja",
                  "value" : "人口動態（年次）",
                  "writing_mode" : "horizontal-tb"
               },
               "url" : "https://data.city.yokohama.lg.jp/dataset/seisaku_jinko-dotai"
            },
            "source_type" : "package",
            "source_url" : "https://data.city.yokohama.lg.jp/api/action/package_show?id=seisaku_jinko-dotai",
            "type" : "license",
            "writing_mode" : "horizontal-tb"
         },
         {
            "alt" : [
               {
                  "dir" : "ltr",
                  "full_url" : "https://creativecommons.org/licenses/by/4.0/",
                  "is_free" : "free",
                  "key" : "CC-BY-4.0",
                  "label" : "Creative Commons Attribution 4.0 International",
                  "lang" : "en",
                  "notice" : {
                     "holder" : {
                        "dir" : "ltr",
                        "lang" : "en",
                        "value" : "神奈川県横浜市",
                        "writing_mode" : "horizontal-tb"
                     },
                     "need_modified_flag" : 1,
                     "template" : {
                        "dir" : "ltr",
                        "lang" : "en",
                        "value" : "この著作物は、以下の著作物を改変して利用しています。\u000A{title}、{holder}\u000Aクリエイティブ・コモンズ・ライセンス 表示4.0 国際\u000A（https://creativecommons.org/licenses/by/4.0/deed.ja）",
                        "writing_mode" : "horizontal-tb"
                     },
                     "template_not_modified" : {
                        "dir" : "ltr",
                        "lang" : "en",
                        "value" : "{title}、{holder}\u000Aクリエイティブ・コモンズ・ライセンス 表示4.0 国際\u000A（https://creativecommons.org/licenses/by/4.0/deed.ja）",
                        "writing_mode" : "horizontal-tb"
                     },
                     "title" : {
                        "dir" : "auto",
                        "lang" : "ja",
                        "value" : "人口動態（年次）",
                        "writing_mode" : "horizontal-tb"
                     },
                     "url" : "https://data.city.yokohama.lg.jp/dataset/seisaku_jinko-dotai"
                  },
                  "type" : "fallback_license",
                  "writing_mode" : "horizontal-tb"
               }
            ],
            "dir" : "ltr",
            "full_url" : "https://data.city.yokohama.lg.jp/terms.html",
            "is_free" : "unknown",
            "key" : "-ddsd-terms-data.city.yokohama.lg.jp",
            "label" : "横浜市オープンデータポータルサイト利用規約 (平成31（2019）年3月)",
            "lang" : "ja",
            "source_type" : "site",
            "source_url" : "https://data.city.yokohama.lg.jp/terms.html",
            "type" : "site_terms",
            "writing_mode" : "horizontal-tb"
         },
         {
            "dir" : "ltr",
            "is_free" : "neutral",
            "key" : "-ddsd-disclaimer",
            "lang" : "ja",
            "notice" : {
               "template" : {
                  "dir" : "ltr",
                  "lang" : "ja",
                  "value" : "これらの法的な表示はソフトウェアにより機械的に抽出・生成したものです。ソフトウェアの制作者はその正確性、完全性、その他を一切保証しません。",
                  "writing_mode" : "horizontal-tb"
               }
            },
            "source_type" : "sniffer",
            "type" : "disclaimer",
            "writing_mode" : "horizontal-tb"
         }
      ]
   },
   "length" : 22126,
   "mirrorzip" : {
      "length" : 12531,
      "set" : "free-3",
      "sha256" : "4133d0f5a41a9723254d8d1990633a9165c66c5274a9d0a22cdd6970c7c3429a"
   },
   "package" : {
      "author" : "統計情報課",
      "ckan_api_url" : "https://data.city.yokohama.lg.jp/api/action/package_show?id=seisaku_jinko-dotai",
      "desc" : "",
      "org" : "政策経営局",
      "page_url" : "https://data.city.yokohama.lg.jp/dataset/seisaku_jinko-dotai",
      "tags" : [
         "統計情報課",
         "政策経営局",
         "市政",
         "人口_世帯数",
         "統計"
      ],
      "time" : 1738890283.49873,
      "title" : "人口動態（年次）"
   },
   "ref_key_text" : "6\u001Cdc3ec5593ede448b7c67e64f3ae24617e5c2f5883ed404ac14e2707573054850\u001Cfree\u001C0\u001C0"
}
